Ezpub/__init__.py
Ezpub/ezpub.py
ezpub_karjakak-1.3.6.dist-info/licenses/LICENSE
ezpub_karjakak-1.3.6.dist-info/METADATA
ezpub_karjakak-1.3.6.dist-info/WHEEL
ezpub_karjakak-1.3.6.dist-info/entry_points.txt
ezpub_karjakak-1.3.6.dist-info/top_level.txt
ezpub_karjakak-1.3.6.dist-info/RECORD
