Metadata-Version: 2.4
Name: Ezpub-karjakak
Version: 1.3.6
Summary: Ezpub is a tool for developer to upload package to PyPI
Home-page: https://github.com/kakkarja/Ezpub
Author: karjakak
Author-email: kakkarja.github@gmail.com
License: MIT License
Classifier: Environment :: Console
Classifier: Environment :: Win32 (MS Windows)
Classifier: Environment :: MacOS X
Classifier: Intended Audience :: Developers
Classifier: Programming Language :: Python :: 3.10
Classifier: License :: OSI Approved :: MIT License
Requires-Python: >=3.10
License-File: LICENSE
Requires-Dist: Twine>=3.4.1
Requires-Dist: Clien-karjakak>=0.0.8
Requires-Dist: filepmon-karjakak>=0.1.0
Requires-Dist: filfla-karjakak>=0.1.0
Requires-Dist: filatt-karjakak>=0.1.0
Requires-Dist: excptr-karjakak>=0.1.0
Dynamic: license-file
